{"hrdebjywvtkmcpga":[{"id":"MAL-2022-3683","sev":"HIGH","r":[{"sInc":"0"}],"src":"OSV"}],"hretokxbpwuilnck":[{"id":"MAL-2022-3684","sev":"HIGH","r":[{"sInc":"0"}],"src":"OSV"}],"hreport-preview":[{"id":"MAL-2023-1521","sev":"HIGH","r":[{"sInc":"0"}],"src":"OSV"}],"hraxisys-notthedevs":[{"id":"MAL-2025-103820","sev":"HIGH","r":[{"sInc":"0"}],"src":"OSV"}],"hrodei":[{"id":"MAL-2025-22740","sev":"HIGH","r":[{"sInc":"0"}],"src":"OSV"}],"hr1pq1wq123":[{"id":"MAL-2025-47062","sev":"HIGH","r":[{"sInc":"0"},{"sInc":"2.0.0"}],"src":"OSV"}],"hrpdesign":[{"id":"MAL-2025-47063","sev":"HIGH","r":[{"sInc":"0"},{"sInc":"1.0.0"}],"src":"OSV"}],"hrphelpall":[{"id":"MAL-2025-47064","sev":"HIGH","r":[{"sInc":"0"}],"src":"OSV"}],"hrpq1wq123":[{"id":"MAL-2025-47065","sev":"HIGH","r":[{"sInc":"0"},{"sInc":"1.0.0"}],"src":"OSV"}],"hrpqvq":[{"id":"MAL-2025-47066","sev":"HIGH","r":[{"sInc":"0"},{"sInc":"3.0.0"}],"src":"OSV"}],"hrpqvq123":[{"id":"MAL-2025-47067","sev":"HIGH","r":[{"sInc":"0"},{"sInc":"1.0.0"}],"src":"OSV"}],"hrpqwq":[{"id":"MAL-2025-47068","sev":"HIGH","r":[{"sInc":"0"},{"sInc":"1.0.0"}],"src":"OSV"}],"hrpqwq123":[{"id":"MAL-2025-47069","sev":"HIGH","r":[{"sInc":"0"},{"sInc":"1.0.0"}],"src":"OSV"}],"hrp987":[{"id":"MAL-2025-47118","sev":"HIGH","r":[{"sInc":"1.0.0"}],"src":"OSV"}],"hrp9873":[{"id":"MAL-2025-47119","sev":"HIGH","r":[{"sInc":"1.0.0"}],"src":"OSV"}],"hrpqvq123111":[{"id":"MAL-2025-47120","sev":"HIGH","r":[{"sInc":"1.0.0"}],"src":"OSV"}],"hrprce":[{"id":"MAL-2025-47121","sev":"HIGH","r":[{"sInc":"1.0.0"}],"src":"OSV"}],"hrprce123":[{"id":"MAL-2025-47122","sev":"HIGH","r":[{"sInc":"1.0.0"}],"src":"OSV"}],"hrm-absence-frontend-deps":[{"id":"MAL-2025-48029","sev":"HIGH","r":[{"sInc":"0"}],"src":"OSV"}],"hrxtable":[{"id":"MAL-2025-6096","sev":"HIGH","r":[{"sInc":"91.90.0"}],"src":"OSV"}]}