{"jzcgnt":[{"id":"MAL-2024-9156","sev":"HIGH","r":[{"sInc":"0"}],"src":"OSV"}],"jzonki-devapptea":[{"id":"MAL-2025-104745","sev":"HIGH","r":[{"sInc":"0"}],"src":"OSV"}],"jz-native-js-bridge":[{"id":"MAL-2025-192817","sev":"HIGH","r":[],"src":"OSV"}],"jz-ui-user":[{"id":"MAL-2025-192818","sev":"HIGH","r":[],"src":"OSV"}],"jz-user-js-bridge":[{"id":"MAL-2025-192819","sev":"HIGH","r":[],"src":"OSV"}],"jzltdokrbsnxpvmi":[{"id":"MAL-2025-24145","sev":"HIGH","r":[{"sInc":"0"}],"src":"OSV"}],"jz-test-npm":[{"id":"MAL-2026-226","sev":"HIGH","r":[{"sInc":"0"}],"src":"OSV"}]}